README.md
setup.py
btt/__init__.py
btt/btt_messenger.py
btt/experiment_manager.py
btt/trial_manager.py
btt/utils.py
btt.egg-info/PKG-INFO
btt.egg-info/SOURCES.txt
btt.egg-info/dependency_links.txt
btt.egg-info/requires.txt
btt.egg-info/top_level.txt
btt/monitor/__init__.py
btt/monitor/monitor.py
btt/monitor/monitor_rule.py
btt/tuner/__init__.py
btt/tuner/tuner.py
btt/tuner/tuner_hpo.py