Metadata-Version: 2.1
Name: btt
Version: 0.0.3
Summary: A small example package
Author: Example Author
Author-email: author@example.com
Classifier: Programming Language :: Python :: 3
Classifier: Operating System :: OS Independent
Requires-Python: >=3.6
